ellphi/__init__.py
ellphi/__init__.pyi
ellphi/__main__.py
ellphi/_solver_python.py
ellphi/_solver_python.pyi
ellphi/_tangency_cpp.py
ellphi/_tangency_cpp.pyi
ellphi/_tangency_cpp_impl.cpp
ellphi/_tangency_cpp_impl.so
ellphi/_tangent_pencil.py
ellphi/_tangent_pencil.pyi
ellphi/_version.py
ellphi/differentiable_solver.py
ellphi/differentiable_solver.pyi
ellphi/ellcloud.py
ellphi/ellcloud.pyi
ellphi/geometry.py
ellphi/geometry.pyi
ellphi/py.typed
ellphi/solver.py
ellphi/solver.pyi
ellphi/visualization.py
ellphi/visualization.pyi
ellphi-0.1.1.post1.dist-info/METADATA
ellphi-0.1.1.post1.dist-info/WHEEL
ellphi-0.1.1.post1.dist-info/entry_points.txt
ellphi-0.1.1.post1.dist-info/licenses/LICENSE
ellphi-0.1.1.post1.dist-info/RECORD
