Metadata-Version: 2.4
Name: ellphi
Version: 0.1.1.post1
Summary: Fast ellipse tangency solver
License: MIT License
License-File: LICENSE
Keywords: topological data analysis,computational geometry,ellipse,tangency
Author: Tomoki Uda
Author-email: tomoki.uda@gmail.com
Requires-Python: >=3.10
Classifier: Development Status :: 3 - Alpha
Classifier: Intended Audience :: Science/Research
Classifier: Topic :: Scientific/Engineering :: Mathematics
Classifier: License :: OSI Approved :: MIT License
Classifier: Programming Language :: Python
Classifier: Programming Language :: Python :: 3
Classifier: Programming Language :: Python :: 3 :: Only
Classifier: Programming Language :: Python :: 3.10
Classifier: Programming Language :: Python :: 3.11
Classifier: Programming Language :: Python :: 3.12
Classifier: Operating System :: OS Independent
Provides-Extra: demo
Requires-Dist: homcloud (>=4.8.0) ; extra == "demo"
Requires-Dist: ipykernel (>=6.28) ; extra == "demo"
Requires-Dist: joblib (>=1.3)
Requires-Dist: jupyterlab (>=4.1) ; extra == "demo"
Requires-Dist: matplotlib (>=3.9)
Requires-Dist: nbformat (>=5.10) ; extra == "demo"
Requires-Dist: numpy (>=1.26)
Requires-Dist: pandas (>=2.2.0) ; extra == "demo"
Requires-Dist: plotly (>=5.22) ; extra == "demo"
Requires-Dist: scipy (>=1.12)
Requires-Dist: seaborn (>=0.13) ; extra == "demo"
Requires-Dist: tqdm (>=4.67.1) ; extra == "demo"
Project-URL: Homepage, https://github.com/t-uda/ellphi
Project-URL: Repository, https://github.com/t-uda/ellphi
